assertlang/__init__.py
assertlang/cli.py
assertlang/client.py
assertlang/config.py
assertlang/exceptions.py
assertlang/sdk.py
assertlang/testing.py
assertlang/transport.py
assertlang/cli/__init__.py
assertlang/cli/error_formatter.py
assertlang/cli/file_helpers.py
assertlang/cli/generate_docs.py
assertlang/cli/progress.py
assertlang/cli/validate_contract.py
assertlang/integrations/__init__.py
assertlang/integrations/crewai/__init__.py
assertlang/integrations/crewai/registry.py
assertlang/integrations/crewai/tools.py
assertlang/integrations/langgraph/__init__.py
assertlang/runtime/__init__.py
assertlang/runtime/contracts.py
assertlang/testing/__init__.py
assertlang/testing/contracts.py
assertlang-3.0.0.dist-info/licenses/LICENSE
cli/__init__.py
cli/dsl_format.py
cli/main.py
cli/mcp.py
cli/promptware_old.py
cli/toolgen.py
cli/formatters/__init__.py
cli/formatters/promptware_dsl_formatter.py
daemon/__init__.py
daemon/deps_utils.py
daemon/gateway.py
daemon/mcpd.py
daemon/uds_shim.py
docs/AI_AGENT_GUIDE.md
docs/ARCHITECTURE.md
docs/BLOCK_PARSING_IMPLEMENTATION_CHECKLIST.md
docs/BLOCK_PARSING_IMPLEMENTATION_EXAMPLE.md
docs/BLOCK_PARSING_RESEARCH.md
docs/CREATE_DEMO_GIF.md
docs/DEVELOPMENT.md
docs/DOTNET_GENERATOR_V2.md
docs/DOTNET_PARSER_V2.md
docs/EXAMPLES_INDEX.md
docs/GO_GENERATOR_V2.md
docs/GO_PARSER_V2.md
docs/INDEX.md
docs/INTEGRATION_TESTING.md
docs/IR_SPECIFICATION.md
docs/NODEJS_GENERATOR_V2.md
docs/NODEJS_PARSER_V2.md
docs/PRODUCTION_READINESS_PLAN.md
docs/PW_DSL_2.0_SPEC.md
docs/PW_LANGUAGE_GUIDE.md
docs/PW_NATIVE_SYNTAX.md
docs/PW_SYNTAX_QUICK_REFERENCE.md
docs/PYTHON_GENERATOR_V2.md
docs/PYTHON_PARSER_V2.md
docs/QUICK_REFERENCE.md
docs/README.md
docs/RESEARCH_NOTES.md
docs/RUST_GENERATOR_V2.md
docs/RUST_PARSER_V2.md
docs/SAFE_PATTERNS.md
docs/TYPE_SYSTEM.md
docs/VS_CODE_EXTENSION.md
docs/WORLD_CLASS_ROADMAP.md
docs/agent-communication-guide.md
docs/agents.md
docs/cheatsheet.md
docs/cli-guide.md
docs/cli-quickstart.md
docs/client-api.md
docs/dependency-management.md
docs/development-guide.md
assertlang-3.0.0.dist-info/METADATA
assertlang-3.0.0.dist-info/WHEEL
assertlang-3.0.0.dist-info/entry_points.txt
assertlang-3.0.0.dist-info/top_level.txt
assertlang-3.0.0.dist-info/RECORD
