Metadata-Version: 2.4
Name: assertlang
Version: 3.0.0
Summary: Executable contracts for multi-agent systems - deterministic coordination across frameworks and languages
Home-page: https://github.com/AssertLang/AssertLang
Author: AssertLang Contributors
Author-email: AssertLang Contributors <hello@assertlang.dev>
Project-URL: Homepage, https://github.com/AssertLang/AssertLang
Project-URL: Documentation, https://github.com/AssertLang/AssertLang/tree/main/docs
Project-URL: Repository, https://github.com/AssertLang/AssertLang
Project-URL: Bug Tracker, https://github.com/AssertLang/AssertLang/issues
Project-URL: Changelog, https://github.com/AssertLang/AssertLang/blob/main/CHANGELOG.md
Requires-Python: >=3.9
License-File: LICENSE
Requires-Dist: requests>=2.31.0
Requires-Dist: tomli>=2.0.0; python_version < "3.11"
Requires-Dist: tomli-w>=1.0.0
Requires-Dist: pyyaml>=6.0.0
Requires-Dist: jsonschema>=4.0.0
Provides-Extra: dev
Requires-Dist: pytest>=7.4.0; extra == "dev"
Requires-Dist: pytest-asyncio>=0.21.0; extra == "dev"
Requires-Dist: pytest-cov>=4.1.0; extra == "dev"
Requires-Dist: pytest-mock>=3.12.0; extra == "dev"
Requires-Dist: black>=23.10.0; extra == "dev"
Requires-Dist: flake8>=6.1.0; extra == "dev"
Requires-Dist: mypy>=1.6.0; extra == "dev"
Requires-Dist: ipython>=8.17.0; extra == "dev"
Requires-Dist: ipdb>=0.13.13; extra == "dev"
Requires-Dist: click>=8.0.0; extra == "dev"
Dynamic: author
Dynamic: home-page
Dynamic: license-file
Dynamic: requires-python
